odoo/addons/account_tax_balance/README.rst
odoo/addons/account_tax_balance/__init__.py
odoo/addons/account_tax_balance/__manifest__.py
odoo/addons/account_tax_balance/hooks.py
odoo/addons/account_tax_balance/i18n/account_tax_balance.pot
odoo/addons/account_tax_balance/i18n/ca.po
odoo/addons/account_tax_balance/i18n/de.po
odoo/addons/account_tax_balance/i18n/es.po
odoo/addons/account_tax_balance/i18n/es_AR.po
odoo/addons/account_tax_balance/i18n/fr.po
odoo/addons/account_tax_balance/i18n/fr_FR.po
odoo/addons/account_tax_balance/i18n/hr_HR.po
odoo/addons/account_tax_balance/i18n/it.po
odoo/addons/account_tax_balance/i18n/nl.po
odoo/addons/account_tax_balance/i18n/nl_NL.po
odoo/addons/account_tax_balance/i18n/pt.po
odoo/addons/account_tax_balance/i18n/pt_BR.po
odoo/addons/account_tax_balance/i18n/ro.po
odoo/addons/account_tax_balance/i18n/sl.po
odoo/addons/account_tax_balance/i18n/tr.po
odoo/addons/account_tax_balance/models/__init__.py
odoo/addons/account_tax_balance/models/account_move.py
odoo/addons/account_tax_balance/models/account_move_line.py
odoo/addons/account_tax_balance/models/account_tax.py
odoo/addons/account_tax_balance/readme/CONTRIBUTORS.md
odoo/addons/account_tax_balance/readme/DESCRIPTION.md
odoo/addons/account_tax_balance/readme/USAGE.md
odoo/addons/account_tax_balance/security/ir.model.access.csv
odoo/addons/account_tax_balance/static/description/icon.png
odoo/addons/account_tax_balance/static/description/index.html
odoo/addons/account_tax_balance/static/description/tax_balance.png
odoo/addons/account_tax_balance/tests/__init__.py
odoo/addons/account_tax_balance/tests/test_account_tax_balance.py
odoo/addons/account_tax_balance/views/account_move_view.xml
odoo/addons/account_tax_balance/views/account_tax_view.xml
odoo/addons/account_tax_balance/wizard/__init__.py
odoo/addons/account_tax_balance/wizard/open_tax_balances.py
odoo/addons/account_tax_balance/wizard/open_tax_balances_view.xml
odoo_addon_account_tax_balance-18.0.1.0.3.4.dist-info/METADATA
odoo_addon_account_tax_balance-18.0.1.0.3.4.dist-info/WHEEL
odoo_addon_account_tax_balance-18.0.1.0.3.4.dist-info/top_level.txt
odoo_addon_account_tax_balance-18.0.1.0.3.4.dist-info/RECORD
