Metadata-Version: 2.1
Name: odoo-addon-account_tax_balance
Version: 18.0.1.0.3.4
Requires-Python: >=3.10
Requires-Dist: odoo-addon-date_range==18.0.*
Requires-Dist: odoo==18.0.*
Summary: Compute tax balances based on date range
Home-page: https://github.com/OCA/account-financial-reporting
License: AGPL-3
Author: Agile Business Group, Therp BV, Tecnativa, ACSONE SA/NV, Odoo Community Association (OCA)
Author-email: support@odoo-community.org
Classifier: Programming Language :: Python
Classifier: Framework :: Odoo
Classifier: Framework :: Odoo :: 18.0
Classifier: License :: OSI Approved :: GNU Affero General Public License v3
Classifier: Development Status :: 6 - Mature
